dataget/__init__.py
dataget/audio/__init__.py
dataget/audio/free_spoken_digit.py
dataget/dataset.py
dataget/image/__init__.py
dataget/image/cifar.py
dataget/image/fashion_mnist.py
dataget/image/imagenet.py
dataget/image/mnist.py
dataget/image/udacity_simulator.py
dataget/kaggle.py
dataget/structured/__init__.py
dataget/structured/movielens.py
dataget/text/__init__.py
dataget/text/imdb_reviews.py
dataget/toy/__init__.py
dataget/toy/spirals.py
dataget/utils.py
dataget-0.4.15.dist-info/LICENSE
dataget-0.4.15.dist-info/WHEEL
dataget-0.4.15.dist-info/METADATA
dataget-0.4.15.dist-info/RECORD
