Metadata-Version: 2.1
Name: dataget
Version: 0.4.15
Summary: A framework-agnostic datasets library for Machine Learning research and education.
Home-page: https://cgarciae.github.io/dataget
License: MIT
Author: Cristian Garcia
Author-email: cgarcia.e88@gmail.com
Requires-Python: >=3.6.1,<4.0.0
Classifier: License :: OSI Approved :: MIT License
Classifier: Programming Language :: Python :: 3
Classifier: Programming Language :: Python :: 3.7
Classifier: Programming Language :: Python :: 3.8
Requires-Dist: aiofiles (>=0.4.0,<0.5.0)
Requires-Dist: httpx (>=0.11.1,<0.12.0)
Requires-Dist: idx2numpy (>=1.2.2,<2.0.0)
Requires-Dist: kaggle (>=1.5.6,<2.0.0)
Requires-Dist: numpy (>=1.18.1,<2.0.0)
Requires-Dist: pandas (>=1.0.1,<2.0.0)
Requires-Dist: tqdm (>=4.42.1,<5.0.0)
Project-URL: Repository, https://github.com/cgarciae/dataget
